mux16_to_1.v
module mux16_to_1(out,a,b,c,d,e,f,g,h,i,j,k,l,m,n,o,p,sel);
input [7:0] a,b,c,d,e,f,g,h,i,j,k,l,m,n,o,p;
input [3:0] sel;
output [7:0] out;
reg [7:0] out;

always @(a or b or c or d or e or f or g or h or i or j or k or m or n or o or p or sel)begin
  case (sel)
    4'b0000: out<=a;
    4'b0001: out<=b;
    4'b0010: out<=c;
    4'b0011: out<=d;
    4'b0100: out<=e;
    4'b0101: out<=f;
    4'b0110: out<=g;
    4'b0111: out<=h;
    4'b1000: out<=i;
    4'b1001: out<=j;
    4'b1010: out<=k;
    4'b1011: out<=l;
    4'b1100: out<=m;
    4'b1101: out<=n;
    4'b1110: out<=o;
    4'b1111: out<=p;
  endcase
end
endmodule

mux_t.v
`include "mux16_to_1.v"

module mux16_to_1_t();

reg [7:0] a,b,c,d,e,f,g,h,i,j,k,l,m,n,o,p;
reg [3:0] sel;
wire [7:0]out;

mux16_to_1 o1(out,a,b,c,d,e,f,g,h,i,j,k,l,m,n,o,p,sel);

initial begin

		$display("Simulation running..."); // Display info on monitor
        $dumpfile("mux16_to_1.vcd"); // Simulation results -> GTKWave
        $dumpvars(0,o1);  // Variables that will be in vcd file
        //$dumpvars(1,a,b,out);  // Variables that will be in vcd file

        $monitor("%d, %d, %d, %d, %d, %d, %d, %d, %d, %d, %d, %d, %d, %d, %d, %d, --> %d, %d",a,b,c,d,e,f,g,h,i,j,k,l,m,n,o,p,sel,out);
		#0 	a = 8'd23; b = 8'd0;  c = 8'd0;  d = 8'd0;  e = 8'd0;  f = 8'd0;  g = 8'd0;  h = 8'd0;  i = 8'd0;  j = 8'd0;  k = 8'd0;  l = 8'd0;  m = 8'd0;  n = 8'd0;  o = 8'd0;  p = 8'd0;   sel = 4'h0; 
		#50 a = 8'd0;  b = 8'd02; c = 8'd0;  d = 8'd0;  e = 8'd0;  f = 8'd0;  g = 8'd0;  h = 8'd0;  i = 8'd0;  j = 8'd0;  k = 8'd0;  l = 8'd0;  m = 8'd0;  n = 8'd0;  o = 8'd0;  p = 8'd0;   sel = 4'h1; 
		#50 a = 8'd0;  b = 8'd0;  c = 8'd03; d = 8'd0;  e = 8'd0;  f = 8'd0;  g = 8'd0;  h = 8'd0;  i = 8'd0;  j = 8'd0;  k = 8'd0;  l = 8'd0;  m = 8'd0;  n = 8'd0;  o = 8'd0;  p = 8'd0;   sel = 4'h2; 
		#50 a = 8'd0;  b = 8'd0;  c = 8'd0;  d = 8'd04; e = 8'd0;  f = 8'd0;  g = 8'd0;  h = 8'd0;  i = 8'd0;  j = 8'd0;  k = 8'd0;  l = 8'd0;  m = 8'd0;  n = 8'd0;  o = 8'd0;  p = 8'd0;   sel = 4'h3; 
		#50 a = 8'd0;  b = 8'd0;  c = 8'd0;  d = 8'd0;  e = 8'd05; f = 8'd0;  g = 8'd0;  h = 8'd0;  i = 8'd0;  j = 8'd0;  k = 8'd0;  l = 8'd0;  m = 8'd0;  n = 8'd0;  o = 8'd0;  p = 8'd0;   sel = 4'h4; 
		#50 a = 8'd0;  b = 8'd0;  c = 8'd0;  d = 8'd0;  e = 8'd0;  f = 8'd06; g = 8'd0;  h = 8'd0;  i = 8'd0;  j = 8'd0;  k = 8'd0;  l = 8'd0;  m = 8'd0;  n = 8'd0;  o = 8'd0;  p = 8'd0;   sel = 4'h5; 
		#50 a = 8'd0;  b = 8'd0;  c = 8'd0;  d = 8'd0;  e = 8'd0;  f = 8'd0;  g = 8'd07; h = 8'd0;  i = 8'd0;  j = 8'd0;  k = 8'd0;  l = 8'd0;  m = 8'd0;  n = 8'd0;  o = 8'd0;  p = 8'd0;   sel = 4'h6; 
        #50 a = 8'd0;  b = 8'd0;  c = 8'd0;  d = 8'd0;  e = 8'd0;  f = 8'd0;  g = 8'd0;  h = 8'd08; i = 8'd0;  j = 8'd0;  k = 8'd0;  l = 8'd0;  m = 8'd0;  n = 8'd0;  o = 8'd0;  p = 8'd0;   sel = 4'h7;
        #50 a = 8'd0;  b = 8'd0;  c = 8'd0;  d = 8'd0;  e = 8'd0;  f = 8'd0;  g = 8'd0;  h = 8'd0;  i = 8'd09; j = 8'd0;  k = 8'd0;  l = 8'd0;  m = 8'd0;  n = 8'd0;  o = 8'd0;  p = 8'd0;   sel = 4'h8;
        #50 a = 8'd0;  b = 8'd0;  c = 8'd0;  d = 8'd0;  e = 8'd0;  f = 8'd0;  g = 8'd0;  h = 8'd0;  i = 8'd0;  j = 8'd10; k = 8'd0;  l = 8'd0;  m = 8'd0;  n = 8'd0;  o = 8'd0;  p = 8'd0;   sel = 4'h9;
        #50 a = 8'd0;  b = 8'd0;  c = 8'd0;  d = 8'd0;  e = 8'd0;  f = 8'd0;  g = 8'd0;  h = 8'd0;  i = 8'd0;  j = 8'd0;  k = 8'd11; l = 8'd0;  m = 8'd0;  n = 8'd0;  o = 8'd0;  p = 8'd0;   sel = 4'ha;
        #50 a = 8'd0;  b = 8'd0;  c = 8'd0;  d = 8'd0;  e = 8'd0;  f = 8'd0;  g = 8'd0;  h = 8'd0;  i = 8'd0;  j = 8'd0;  k = 8'd0;  l = 8'd12; m = 8'd0;  n = 8'd0;  o = 8'd0;  p = 8'd0;   sel = 4'hb;
        #50 a = 8'd0;  b = 8'd0;  c = 8'd0;  d = 8'd0;  e = 8'd0;  f = 8'd0;  g = 8'd0;  h = 8'd0;  i = 8'd0;  j = 8'd0;  k = 8'd0;  l = 8'd0;  m = 8'd13; n = 8'd0;  o = 8'd0;  p = 8'd0;   sel = 4'hc;
        #50 a = 8'd0;  b = 8'd0;  c = 8'd0;  d = 8'd0;  e = 8'd0;  f = 8'd0;  g = 8'd0;  h = 8'd0;  i = 8'd0;  j = 8'd0;  k = 8'd0;  l = 8'd0;  m = 8'd0;  n = 8'd14; o = 8'd0;  p = 8'd0;   sel = 4'hd;
        #50 a = 8'd0;  b = 8'd0;  c = 8'd0;  d = 8'd0;  e = 8'd0;  f = 8'd0;  g = 8'd0;  h = 8'd0;  i = 8'd0;  j = 8'd0;  k = 8'd0;  l = 8'd0;  m = 8'd0;  n = 8'd0;  o = 8'd15; p = 8'd0;   sel = 4'he;
        #50 a = 8'd0;  b = 8'd0;  c = 8'd0;  d = 8'd0;  e = 8'd0;  f = 8'd0;  g = 8'd0;  h = 8'd0;  i = 8'd0;  j = 8'd0;  k = 8'd0;  l = 8'd0;  m = 8'd0;  n = 8'd0;  o = 8'd0;  p = 8'd16;  sel = 4'hf; 
		#50 $finish;
end

endmodule

mux16_to_1.vcd
$date
	Sat May 16 01:32:55 2020
$end
$version
	Icarus Verilog
$end
$timescale
	1s
$end
$scope module mux16_to_1_t $end
$scope module o1 $end
$var wire 8 ! a [7:0] $end
$var wire 8 " b [7:0] $end
$var wire 8 # c [7:0] $end
$var wire 8 $ d [7:0] $end
$var wire 8 % e [7:0] $end
$var wire 8 & f [7:0] $end
$var wire 8 ' g [7:0] $end
$var wire 8 ( h [7:0] $end
$var wire 8 ) i [7:0] $end
$var wire 8 * j [7:0] $end
$var wire 8 + k [7:0] $end
$var wire 8 , l [7:0] $end
$var wire 8 - m [7:0] $end
$var wire 8 . n [7:0] $end
$var wire 8 / o [7:0] $end
$var wire 8 0 p [7:0] $end
$var wire 4 1 sel [3:0] $end
$var reg 8 2 out [7:0] $end
$upscope $end
$upscope $end
$enddefinitions $end
#0
$dumpvars
b10111 2
b0 1
b0 0
b0 /
b0 .
b0 -
b0 ,
b0 +
b0 *
b0 )
b0 (
b0 '
b0 &
b0 %
b0 $
b0 #
b0 "
b10111 !
$end
#50
b10 2
b1 1
b10 "
b0 !
#100
b11 2
b10 1
b11 #
b0 "
#150
b100 2
b11 1
b100 $
b0 #
#200
b101 2
b100 1
b101 %
b0 $
#250
b110 2
b101 1
b110 &
b0 %
#300
b111 2
b110 1
b111 '
b0 &
#350
b1000 2
b111 1
b1000 (
b0 '
#400
b1001 2
b1000 1
b1001 )
b0 (
#450
b1010 2
b1001 1
b1010 *
b0 )
#500
b1011 2
b1010 1
b1011 +
b0 *
#550
b1100 2
b1011 1
b1100 ,
b0 +
#600
b1101 2
b1100 1
b1101 -
b0 ,
#650
b1110 2
b1101 1
b1110 .
b0 -
#700
b1111 2
b1110 1
b1111 /
b0 .
#750
b10000 2
b1111 1
b10000 0
b0 /
