nand_8bit.v

module nand_8bit(output [7:0] out, input [7:0] a, b);

nand (out[0], a[0], b[0]);
nand (out[1], a[1], b[1]);
nand (out[2], a[2], b[2]);
nand (out[3], a[3], b[3]);
nand (out[4], a[4], b[4]);
nand (out[5], a[5], b[5]);
nand (out[6], a[6], b[6]);
nand (out[7], a[7], b[7]);


endmodule

nand_t8bit.v
`include "nand_8bit.v"

module nand_t8bit();

reg [7:0] a,b;
wire [7:0]out;

nand_8bit a1(out,a,b);

initial begin

		$display("Simulation running..."); // Display info on monitor
        $dumpfile("nand_t8bit.vcd"); // Simulation results -> GTKWave
        $dumpvars(0,a1);  // Variables that will be in vcd file
        $dumpvars(1,a,b,out);  // Variables that will be in vcd file

        $monitor("%b NAND %b  = %b", a, b, out);
		#0 	a = 8'b11111111; b = 8'b01001010; 
		#50 a = 8'b00000000; b = 8'b11111111; 
		#50 a = 8'b11111111; b = 8'b10000001; 
		#50 a = 8'b01010101; b = 8'b10101010; 
		#50 a = 8'b10000010; b = 8'b00011110; 
		#50 a = 8'b10000100; b = 8'b01000000; 
		#50 a = 8'b10001000; b = 8'b10000101; 
		#50 a = 8'b10010000; b = 8'b10010111; 
		#50 $finish;
end

endmodule

nand_t8bit.vcd
$date
	Tue May 12 01:21:16 2020
$end
$version
	Icarus Verilog
$end
$timescale
	1s
$end
$scope module nand_t8bit $end
$scope module a1 $end
$var wire 8 ! a [7:0] $end
$var wire 8 " b [7:0] $end
$var wire 8 # out [7:0] $end
$upscope $end
$upscope $end
$scope module nand_t8bit $end
$var reg 8 $ a [7:0] $end
$upscope $end
$scope module nand_t8bit $end
$var reg 8 % b [7:0] $end
$upscope $end
$scope module nand_t8bit $end
$var wire 8 & out [7:0] $end
$upscope $end
$enddefinitions $end
#0
$dumpvars
b10110101 &
b1001010 %
b11111111 $
b10110101 #
b1001010 "
b11111111 !
$end
#50
b11111111 #
b11111111 &
b11111111 "
b11111111 %
b0 !
b0 $
#100
b1111110 #
b1111110 &
b10000001 "
b10000001 %
b11111111 !
b11111111 $
#150
b11111111 #
b11111111 &
b10101010 "
b10101010 %
b1010101 !
b1010101 $
#200
b11111101 #
b11111101 &
b11110 "
b11110 %
b10000010 !
b10000010 $
#250
b11111111 #
b11111111 &
b1000000 "
b1000000 %
b10000100 !
b10000100 $
#300
b1111111 #
b1111111 &
b10000101 "
b10000101 %
b10001000 !
b10001000 $
#350
b1101111 #
b1101111 &
b10010111 "
b10010111 %
b10010000 !
b10010000 $
