or_8bit.v

module or_8bit(output [7:0] out, input [7:0] a, b);

or (out[1], a[1], b[1]);
or (out[0], a[0], b[0]);
or (out[2], a[2], b[2]);
or (out[3], a[3], b[3]);
or (out[4], a[4], b[4]);
or (out[5], a[5], b[5]);
or (out[6], a[6], b[6]);
or (out[7], a[7], b[7]);


endmodule

or_t8bit.v
`include "or_8bit.v"

module or_t8bit();

reg [7:0] a,b;
wire [7:0]out;

or_8bit o1(out,a,b);

initial begin

		$display("Simulation running..."); // Display info on monitor
        $dumpfile("or_t8bit.vcd"); // Simulation results -> GTKWave
        $dumpvars(0,o1);  // Variables that will be in vcd file
        $dumpvars(1,a,b,out);  // Variables that will be in vcd file

        $monitor("%b OR %b  = %b", a, b, out);
		#0 	a = 8'b11111111; b = 8'b01001010; 
		#50 a = 8'b00000000; b = 8'b11111111; 
		#50 a = 8'b11111111; b = 8'b10000001; 
		#50 a = 8'b01010101; b = 8'b10101010; 
		#50 a = 8'b00000000; b = 8'b00000000; 
		#50 a = 8'b10000100; b = 8'b01000000; 
		#50 a = 8'b10001000; b = 8'b10000101; 
		#50 a = 8'b10010000; b = 8'b10010111; 
		#50 $finish;
end

endmodule

or_t8bit.vcd
$date
	Tue May 12 01:16:43 2020
$end
$version
	Icarus Verilog
$end
$timescale
	1s
$end
$scope module or_t8bit $end
$scope module o1 $end
$var wire 8 ! a [7:0] $end
$var wire 8 " b [7:0] $end
$var wire 8 # out [7:0] $end
$upscope $end
$upscope $end
$scope module or_t8bit $end
$var reg 8 $ a [7:0] $end
$upscope $end
$scope module or_t8bit $end
$var reg 8 % b [7:0] $end
$upscope $end
$scope module or_t8bit $end
$var wire 8 & out [7:0] $end
$upscope $end
$enddefinitions $end
#0
$dumpvars
b11111111 &
b1001010 %
b11111111 $
b11111111 #
b1001010 "
b11111111 !
$end
#50
b11111111 "
b11111111 %
b0 !
b0 $
#100
b10000001 "
b10000001 %
b11111111 !
b11111111 $
#150
b10101010 "
b10101010 %
b1010101 !
b1010101 $
#200
b0 #
b0 &
b0 "
b0 %
b0 !
b0 $
#250
b11000100 #
b11000100 &
b1000000 "
b1000000 %
b10000100 !
b10000100 $
#300
b10001101 #
b10001101 &
b10000101 "
b10000101 %
b10001000 !
b10001000 $
#350
b10010111 #
b10010111 &
b10010111 "
b10010111 %
b10010000 !
b10010000 $
