FA.v

module FA(Cout,Sum,A,B,Cin);
input A,B,Cin;
output Cout,Sum;
wire w1,w2,w3,w4;

xor x1(w1,A,B);
xor x2(Sum,w1,Cin);

and a1(w2,A,B);
and a2(w3,A,Cin);
and a3(w4,B,Cin);
or o1(Cout,w2,w3,w4);

endmodule

RCA_8bit.v
`include "FA.v"

module RCA_8bit(Cout,Sum,A,B,Cin);
input [7:0] A,B;
input Cin;
output Cout;
output [7:0] Sum;

wire [6:0] w;
wire [7:0] z;

xor (z[0],B[0], Cin);
xor (z[1],B[1], Cin);
xor (z[2],B[2], Cin);
xor (z[3],B[3], Cin);
xor (z[4],B[4], Cin);
xor (z[5],B[5], Cin);
xor (z[6],B[6], Cin);
xor (z[7],B[7], Cin);

FA FA0(w[0],Sum[0],A[0],z[0],Cin);
FA FA1(w[1],Sum[1],A[1],z[1],w[0]);
FA FA2(w[2],Sum[2],A[2],z[2],w[1]);
FA FA3(w[3],Sum[3],A[3],z[3],w[2]);
FA FA4(w[4],Sum[4],A[4],z[4],w[3]);
FA FA5(w[5],Sum[5],A[5],z[5],w[4]);
FA FA6(w[6],Sum[6],A[6],z[6],w[5]);
FA FA7(Cout,Sum[7],A[7],z[7],w[6]);

endmodule

RCA_t8bit.v
`include "RCA_8bit.v"

module RCA_t8bit;

reg [7:0] A,B;
reg Cin;
wire Cout;
wire [7:0] Sum;

integer handle3;
integer desc3;

initial 
    begin
        handle3 = $fopen("RCA4_tb1.txt");
        #400 $finish;
    end

always 
    begin
    desc3 = handle3;
    #50 $fdisplay(desc3,"%b, %b,%b, %b%b", A, B, Cin, Cout,Sum ); 
    end

   initial
   
     begin
		$display("Simulation running..."); // Display info on monitor
        $dumpfile("RCA4_tb1.vcd"); // Simulation results -> GTKWave
        $dumpvars(0,RCA01);  // Variables that will be in vcd file

        $monitor("%d + %d + %d = %d", A, B, Cin,Sum);
		#0 	A = 8'b10010001; B = 8'b01010011; Cin = 1'b0;
		#50 A = 8'd24;        B = 8'd20;       Cin = 1'b1;
		#50 A = 8'd3;        B = 8'd0;        Cin = 1'b0;
		#50 A = 8'd7;        B = 8'd3;        Cin = 1'b1;
		#50 A = 8'd11;       B = 8'd3;        Cin = 1'b0;
		#50 A = 8'd233;      B = 8'd44;       Cin = 1'b1;
		#50 A = 8'd87;       B = 8'd20;       Cin = 1'b0;
		#50 A = 8'd99;       B = 8'd10;       Cin = 1'b1;
		#50 $finish;
     end

RCA_8bit RCA01(Cout,Sum,A,B,Cin);

endmodule

RCA4_tb1.vcd
$date
	Fri May 15 20:09:20 2020
$end
$version
	Icarus Verilog
$end
$timescale
	1s
$end
$scope module RCA_t8bit $end
$scope module RCA01 $end
$var wire 8 ! A [7:0] $end
$var wire 8 " B [7:0] $end
$var wire 1 # Cin $end
$var wire 8 $ z [7:0] $end
$var wire 7 % w [6:0] $end
$var wire 8 & Sum [7:0] $end
$var wire 1 ' Cout $end
$scope module FA0 $end
$var wire 1 ( A $end
$var wire 1 ) B $end
$var wire 1 # Cin $end
$var wire 1 * Cout $end
$var wire 1 + Sum $end
$var wire 1 , w1 $end
$var wire 1 - w2 $end
$var wire 1 . w3 $end
$var wire 1 / w4 $end
$upscope $end
$scope module FA1 $end
$var wire 1 0 A $end
$var wire 1 1 B $end
$var wire 1 2 Cin $end
$var wire 1 3 Cout $end
$var wire 1 4 Sum $end
$var wire 1 5 w1 $end
$var wire 1 6 w2 $end
$var wire 1 7 w3 $end
$var wire 1 8 w4 $end
$upscope $end
$scope module FA2 $end
$var wire 1 9 A $end
$var wire 1 : B $end
$var wire 1 ; Cin $end
$var wire 1 < Cout $end
$var wire 1 = Sum $end
$var wire 1 > w1 $end
$var wire 1 ? w2 $end
$var wire 1 @ w3 $end
$var wire 1 A w4 $end
$upscope $end
$scope module FA3 $end
$var wire 1 B A $end
$var wire 1 C B $end
$var wire 1 D Cin $end
$var wire 1 E Cout $end
$var wire 1 F Sum $end
$var wire 1 G w1 $end
$var wire 1 H w2 $end
$var wire 1 I w3 $end
$var wire 1 J w4 $end
$upscope $end
$scope module FA4 $end
$var wire 1 K A $end
$var wire 1 L B $end
$var wire 1 M Cin $end
$var wire 1 N Cout $end
$var wire 1 O Sum $end
$var wire 1 P w1 $end
$var wire 1 Q w2 $end
$var wire 1 R w3 $end
$var wire 1 S w4 $end
$upscope $end
$scope module FA5 $end
$var wire 1 T A $end
$var wire 1 U B $end
$var wire 1 V Cin $end
$var wire 1 W Cout $end
$var wire 1 X Sum $end
$var wire 1 Y w1 $end
$var wire 1 Z w2 $end
$var wire 1 [ w3 $end
$var wire 1 \ w4 $end
$upscope $end
$scope module FA6 $end
$var wire 1 ] A $end
$var wire 1 ^ B $end
$var wire 1 _ Cin $end
$var wire 1 ` Cout $end
$var wire 1 a Sum $end
$var wire 1 b w1 $end
$var wire 1 c w2 $end
$var wire 1 d w3 $end
$var wire 1 e w4 $end
$upscope $end
$scope module FA7 $end
$var wire 1 f A $end
$var wire 1 g B $end
$var wire 1 h Cin $end
$var wire 1 ' Cout $end
$var wire 1 i Sum $end
$var wire 1 j w1 $end
$var wire 1 k w2 $end
$var wire 1 l w3 $end
$var wire 1 m w4 $end
$upscope $end
$upscope $end
$upscope $end
$enddefinitions $end
#0
$dumpvars
0m
0l
0k
1j
1i
0h
0g
1f
0e
0d
0c
1b
1a
0`
0_
1^
0]
0\
0[
0Z
0Y
1X
0W
1V
0U
0T
0S
0R
1Q
0P
0O
1N
0M
1L
1K
0J
0I
0H
0G
0F
0E
0D
0C
0B
0A
0@
0?
0>
1=
0<
1;
0:
09
18
07
06
15
04
13
12
11
00
0/
0.
1-
0,
0+
1*
1)
1(
0'
b11100100 &
b10011 %
b1010011 $
0#
b1010011 "
b10010001 !
$end
#50
1'
1m
1h
1`
1R
0a
1e
1M
1V
1_
1E
0O
1N
0X
b1111011 %
1W
1H
1P
0Q
1Y
1\
0F
0i
1C
0L
1U
1g
1,
0-
0G
1j
b11101011 $
b100 &
0+
1/
0(
1B
0f
1#
b10100 "
b11000 !
#100
0=
0;
03
02
0_
0h
0*
0W
0a
0`
0i
0'
0M
0V
08
0Y
0\
0b
0e
0j
0m
14
0F
0E
0O
b0 %
0N
0)
01
0C
0U
0^
0g
1,
0-
15
06
07
0G
0H
0P
0R
b0 $
b11 &
1+
0/
1(
10
0B
0K
0#
b0 "
b11 !
#150
1'
1m
1h
1`
1e
1_
1W
1\
1V
1N
1S
1M
1E
1@
1A
1J
1;
1D
13
1<
0F
0O
0X
0a
0i
04
17
1?
1G
1P
1Y
1b
1j
12
1=
1:
1C
1L
1U
1^
1g
b1111111 %
1*
0>
b11111100 $
b100 &
0+
1.
19
1#
b11 "
b111 !
#200
0M
0E
14
18
0D
0V
0_
0h
0<
0O
0N
0X
0W
0a
0`
0i
0'
17
0,
1-
05
16
0A
0J
0P
0S
0Y
0\
0b
0e
0j
0m
12
1=
1F
1)
11
0:
0C
0L
0U
0^
0g
b11 %
1*
0>
0?
0@
1G
0H
0I
b11 $
b1110 &
0+
0.
09
1B
0#
b1011 !
#250
1l
1m
1h
1O
b1000011 %
1`
1'
1P
1c
1k
04
1X
0a
1i
1L
1^
1g
15
06
07
1Y
0b
0j
b11010011 $
b10111101 &
1+
1.
1/
00
1T
1]
1f
1#
b101100 "
b11101001 !
#300
0;
03
02
0h
0*
1a
0`
0'
1D
1V
1,
0-
08
1?
0A
1b
0c
0m
14
0=
1<
1F
0O
b10100 %
1N
1X
0i
0)
01
1:
0^
0g
15
06
07
0>
0@
0G
0P
1Q
0Y
0j
0k
0l
b10100 $
b1101011 &
1+
0.
0/
10
19
0B
1K
0T
0f
0#
b10100 "
b1010111 !
#350
1'
1A
1m
1;
1h
13
1F
1d
1e
1`
0i
04
17
1D
0V
1_
0,
1-
1/
1Z
0\
0b
1c
1j
12
0=
1<
1O
0N
0X
1W
1)
1U
1^
1g
b1100111 %
1*
1>
0?
1P
0Q
0Y
0[
b11110101 $
b1011001 &
1+
1.
09
0K
1T
1#
b1010 "
b1100011 !
